renderj2/__init__.py
renderj2/renderj2.py
renderj2-1.2.2.dist-info/LICENSE
renderj2-1.2.2.dist-info/METADATA
renderj2-1.2.2.dist-info/WHEEL
renderj2-1.2.2.dist-info/entry_points.txt
renderj2-1.2.2.dist-info/RECORD
